anilistWrapPY/__init__.py
anilistWrapPY/Airing/graphql.py
anilistWrapPY/Airing/request.py
anilistWrapPY/Airing/types.py
anilistWrapPY/Anime/graphql.py
anilistWrapPY/Anime/request.py
anilistWrapPY/Anime/types.py
anilistWrapPY/Character/graphql.py
anilistWrapPY/Character/request.py
anilistWrapPY/Character/types.py
anilistWrapPY/client.py
anilistWrapPY/errors/__init__.py
anilistWrapPY/errors/ex_class.py
anilistWrapPY/errors/types.py
anilistWrapPY/Manga/graphql.py
anilistWrapPY/Manga/request.py
anilistWrapPY/Manga/types.py
anilistWrapPY/Media/graphql.py
anilistWrapPY/Media/request.py
anilistWrapPY/Media/types.py
anilistWrapPY/User/graphql.py
anilistWrapPY/User/request.py
anilistWrapPY/User/types.py
anilistwrappy-0.0.16.dist-info/LICENSE
anilistwrappy-0.0.16.dist-info/WHEEL
anilistwrappy-0.0.16.dist-info/METADATA
anilistwrappy-0.0.16.dist-info/RECORD
