Metadata-Version: 2.1
Name: anilistwrappy
Version: 0.0.16
Summary: An API Wrapper for Official Anilist.co GraphQL API
Home-page: https://github.com/Dank-del/anilistWrapPY
License: Unlicense License
Keywords: anilist,wrapper,anilist.co,graphql,api
Author: Sayan Biswas
Author-email: sayan@pokurt.me
Requires-Python: >=3.7,<4.0
Classifier: License :: Other/Proprietary License
Classifier: Programming Language :: Python :: 3
Classifier: Programming Language :: Python :: 3.10
Classifier: Programming Language :: Python :: 3.7
Classifier: Programming Language :: Python :: 3.8
Classifier: Programming Language :: Python :: 3.9
Requires-Dist: httpx (>=0.18.2,<0.19.0)
Requires-Dist: pydantic (>=1.9.1,<2.0.0)
